MANIFEST.in
README.rst
requirements.txt
setup.cfg
setup.py
djmicrosip_utilerias/__init__.py
djmicrosip_utilerias/__init__.pyc
djmicrosip_utilerias/config.pyc
djmicrosip_utilerias/forms.pyc
djmicrosip_utilerias/models.pyc
djmicrosip_utilerias/urls.pyc
djmicrosip_utilerias/views.pyc
djmicrosip_utilerias.egg-info/PKG-INFO
djmicrosip_utilerias.egg-info/SOURCES.txt
djmicrosip_utilerias.egg-info/dependency_links.txt
djmicrosip_utilerias.egg-info/requires.txt
djmicrosip_utilerias.egg-info/top_level.txt
djmicrosip_utilerias/static/djmicrosip_utilerias/js/actualizar_margenes.js
djmicrosip_utilerias/templates/djmicrosip_utilerias/actualiza_margenes.html
djmicrosip_utilerias/templates/djmicrosip_utilerias/base.html
djmicrosip_utilerias/templates/djmicrosip_utilerias/index.html